LICENSE
README.md
setup.cfg
setup.py
Rafflesia/AudioManager.py
Rafflesia/GraphicsManager.py
Rafflesia/IOManager.py
Rafflesia/TextManager.py
Rafflesia/TimingManager.py
Rafflesia/UtilsManager.py
Rafflesia/__init__.py
Rafflesia.egg-info/PKG-INFO
Rafflesia.egg-info/SOURCES.txt
Rafflesia.egg-info/dependency_links.txt
Rafflesia.egg-info/top_level.txt
Rafflesia/Audio/__init__.py
Rafflesia/Audio/busy.py
Rafflesia/Audio/effects.py
Rafflesia/Audio/load.py
Rafflesia/Audio/pause.py
Rafflesia/Audio/play.py
Rafflesia/Audio/pos.py
Rafflesia/Audio/queue.py
Rafflesia/Audio/rewind.py
Rafflesia/Audio/stop.py
Rafflesia/Audio/unpause.py
Rafflesia/Audio/volume.py
Rafflesia/Graphics/__init__.py
Rafflesia/Graphics/td_windows.py
Rafflesia/Resources/rafflesia.ico
Rafflesia/Utils/__init__.py
Rafflesia/Utils/build.py
Rafflesia/Utils/requirements_txt.py